Workbook

Sheet How to use
A1: PRISMA tracking sheet
A2: Project | B2: Privacy-Preserving Heart Disease Risk Prediction Using FHE · COMP4101 Practicum · UDST
A3: Goes with | B3: SLR_Protocol_v3 + SLR_Protocol_v4_changes.md (team roles, criteria I1–I5 and E1–E6)
A5: Colour legend
A6: Yellow cells | B6: Type here. These are the only cells anyone should edit.
A7: Grey cells | B7: Calculated automatically. Do not type over them.
A9: Pairs
A10: Pair 1 | B10: Saif (screener 1) and Naif (screener 2): IEEE Xplore, Set 1, synthesis RQ1 and RQ4
A11: Pair 2 | B11: Sarim (screener 1) and Hassan (screener 2): PubMed, Set 2, synthesis RQ3
A12: Pair 3 | B12: Khalid (screener 1) and Abdullah (screener 2): Scopus, Set 3, synthesis RQ2
A14: Who fills what
A15: Search Log | B15: The first person in each pair types the search row on the day it is run; the partner re-runs it and ticks 'Confirmed by'.
A16: PRISMA Counts | B16: Hassan types 'Duplicate records removed' after de-duplication (done by script, 10 Oct 2026; see research/slr/dedup/). Everything else on that tab fills itself.
A17: Screening Log | B17: Hassan pastes one row per de-duplicated record and assigns it to Pair 1, 2 or 3 (split evenly, at random). Screener 1 fills column G and screener 2 fills column H, independently. If one says Exclude and the other does not, the row shows 'Pending' and the tie-breaker fills 'Resolved decision' (Naif for Pairs 2 and 3, Abdullah for Pair 1).
A18: Full text | B18: Each pair splits its surviving papers between its two members: put your name in 'Full-text reader'. The partner checks every exclusion.
A19: Snowballing | B19: Papers found in reference lists of included studies: add them with Source = Snowballing. They skip title/abstract screening and go straight to full text. Known papers that no database search retrieved (Kim JMIR 2018) use Source = Other sources and are treated the same way.
A21: Rules
A22: Include vs Maybe | B22: If neither screener says Exclude, the record goes to full text automatically. Only Exclude-vs-not disagreements need resolving.
A23: Full text not available | B23: Set 'Full text retrieved?' to No. That is exclusion E5, so leave the decision and code columns empty.
A24: Excluding at full text | B24: Set 'Full-text decision' to Exclude and pick a code (E1, E2, E3, E4 or E6). Every exclusion needs a code.
A25: Checks | B25: The PRISMA Counts tab shows OK or a warning beside each check. Fix warnings before the numbers go into a report.
A27: Example Screening Log row | B27: (format only; do not copy into the log)
A28: Record ID | B28: S-001
A29: Title | B29: Secure logistic regression based on homomorphic encryption: design and evaluation
A30: Authors | B30: Kim M; Song Y; Wang S; Xia Y; Jiang X
A31: Year | B31: 2018
A32: Source | B32: Scopus
A33: Pair | B33: Pair 3
A34: Screener 1 decision | B34: Include
... A36: Agree? | B36: Yes
A37: Resolved decision
A38: Final T/A | B38: Include
A39: Full-text reader | B39: Khalid
A40: Full text retrieved? | B40: Yes
A41: Full-text decision | B41: Include
A42: Exclusion code
A43: Notes | B43: Search-check paper

Sheet PRISMA Counts
A1: PRISMA 2020 flow counts
A2: Labels follow the PRISMA 2020 flow diagram boxes, so each number can be copied straight into the diagram.
A4: Identification (databases)
A5: Records identified: IEEE Xplore | B5: ='Search Log'!H2 -> 337 | C5: From Search Log
A6: Records identified: PubMed | B6: ='Search Log'!H3 -> 172 | C6: From Search Log
A7: Records identified: Scopus | B7: ='Search Log'!H4 -> 1017 | C7: From Search Log
A8: Records identified: total | B8: =SUM(B5:B7) -> 1526
A9: Duplicate records removed | B9: 482 | C9: Typed by Hassan after de-duplication by script (10 Oct 2026; see research/slr/dedup/)
A10: Records to screen (total minus duplicates) | B10: =B8-B9 -> 1044
A11: Screening (databases)
A12: Records screened (rows in Screening Log) | B12: =COUNTIFS('Screening Log'!$A$2:$A$1046,"<>",'Screening Log'!$E$2:$E$1046,"<>Snowballing",'Screening Log'!$E$2:$E$1046,"<>Other sources") -> 1044 | C12: Should equal records to screen, see checks
A13: Records excluded at title/abstract | B13: =COUNTIFS('Screening Log'!$A$2:$A$1046,"<>",'Screening Log'!$E$2:$E$1046,"<>Snowballing",'Screening Log'!$E$2:$E$1046,"<>Other sources",'Screening Log'!$K$2:$K$1046,"Exclude") -> 0 | C13: Uses the final T/A decision
A14: Title/abstract decisions not final yet | B14: =B12-B13-B15 -> 1044 | C14: Waiting for a screener, or Pending a tie-break
A15: Reports sought for retrieval | B15: =COUNTIFS('Screening Log'!$A$2:$A$1046,"<>",'Screening Log'!$E$2:$E$1046,"<>Snowballing",'Screening Log'!$E$2:$E$1046,"<>Other sources",'Screening Log'!$K$2:$K$1046,"Include")+COUNTIFS('Screening Log'!$A$2:$A$1046,"<>",'Screening Log'!$E$2:$E$1046,"<>Snowballing",'Screening Log'!$E$2:$E$1046,"<>Other sources",'Screening Log'!$K$2:$K$1046,"Maybe") -> 0 | C15: Include + Maybe go to full text
A16: Reports not retrieved (E5) | B16: =COUNTIFS('Screening Log'!$A$2:$A$1046,"<>",'Screening Log'!$E$2:$E$1046,"<>Snowballing",'Screening Log'!$E$2:$E$1046,"<>Other sources",'Screening Log'!$M$2:$M$1046,"No") -> 0
A17: Reports assessed for eligibility | B17: =B15-B16 -> 0
A18: Reports excluded: E1 other privacy technique only | B18: =COUNTIFS('Screening Log'!$A$2:$A$1046,"<>",'Screening Log'!$E$2:$E$1046,"<>Snowballing",'Screening Log'!$E$2:$E$1046,"<>Other sources",'Screening Log'!$N$2:$N$1046,"Exclude",'Screening Log'!$O$2:$O$1046,"E1") -> 0
A19: Reports excluded: E2 not health data | B19: =COUNTIFS('Screening Log'!$A$2:$A$1046,"<>",'Screening Log'!$E$2:$E$1046,"<>Snowballing",'Screening Log'!$E$2:$E$1046,"<>Other sources",'Screening Log'!$N$2:$N$1046,"Exclude",'Screening Log'!$O$2:$O$1046,"E2") -> 0
A20: Reports excluded: E3 purely theoretical | B20: =COUNTIFS('Screening Log'!$A$2:$A$1046,"<>",'Screening Log'!$E$2:$E$1046,"<>Snowballing",'Screening Log'!$E$2:$E$1046,"<>Other sources",'Screening Log'!$N$2:$N$1046,"Exclude",'Screening Log'!$O$2:$O$1046,"E3") -> 0
A21: Reports excluded: E4 survey, review, thesis, etc. | B21: =COUNTIFS('Screening Log'!$A$2:$A$1046,"<>",'Screening Log'!$E$2:$E$1046,"<>Snowballing",'Screening Log'!$E$2:$E$1046,"<>Other sources",'Screening Log'!$N$2:$N$1046,"Exclude",'Screening Log'!$O$2:$O$1046,"E4") -> 0
A22: Reports excluded: E6 duplicate or earlier version | B22: =COUNTIFS('Screening Log'!$A$2:$A$1046,"<>",'Screening Log'!$E$2:$E$1046,"<>Snowballing",'Screening Log'!$E$2:$E$1046,"<>Other sources",'Screening Log'!$N$2:$N$1046,"Exclude",'Screening Log'!$O$2:$O$1046,"E6") -> 0
A23: Reports excluded at full text: total | B23: =SUM(B18:B22) -> 0
A24: Studies included from databases | B24: =COUNTIFS('Screening Log'!$A$2:$A$1046,"<>",'Screening Log'!$E$2:$E$1046,"<>Snowballing",'Screening Log'!$E$2:$E$1046,"<>Other sources",'Screening Log'!$N$2:$N$1046,"Include") -> 0
A25: Full-text decisions still pending | B25: =B17-B23-B24 -> 0 | C25: Not decided yet, or excluded without a code
A26: Other methods (backward snowballing, other sources)
A27: Records identified from reference lists and other sources | B27: =SUM(COUNTIFS('Screening Log'!$A$2:$A$1046,"<>",'Screening Log'!$E$2:$E$1046,{"Snowballing","Other sources"})) -> 1 | C27: Source = Snowballing or Other sources
A28: Reports not retrieved | B28: =SUM(COUNTIFS('Screening Log'!$A$2:$A$1046,"<>",'Screening Log'!$E$2:$E$1046,{"Snowballing","Other sources"},'Screening Log'!$M$2:$M$1046,"No")) -> 0
A29: Reports assessed for eligibility | B29: =B27-B28 -> 1
A30: Reports excluded | B30: =SUM(COUNTIFS('Screening Log'!$A$2:$A$1046,"<>",'Screening Log'!$E$2:$E$1046,{"Snowballing","Other sources"},'Screening Log'!$N$2:$N$1046,"Exclude")) -> 0 | C30: Reasons are in the Screening Log
A31: Studies included from snowballing | B31: =SUM(COUNTIFS('Screening Log'!$A$2:$A$1046,"<>",'Screening Log'!$E$2:$E$1046,{"Snowballing","Other sources"},'Screening Log'!$N$2:$N$1046,"Include")) -> 0
A32: Included
A33: Total studies included in review | B33: =B24+B31 -> 0 | C33: This is the number your synthesis is based on
A34: Screening agreement (title/abstract, both screeners)
A35: Records with both decisions | B35: =COUNTIFS('Screening Log'!$A$2:$A$1046,"<>",'Screening Log'!$E$2:$E$1046,"<>Snowballing",'Screening Log'!$E$2:$E$1046,"<>Other sources",'Screening Log'!$G$2:$G$1046,"<>",'Screening Log'!$H$2:$H$1046,"<>") -> 0
A36: Agreements (same decision) | B36: =COUNTIFS('Screening Log'!$I$2:$I$1046,"Yes") -> 0
A37: Percent agreement | B37: =IF(B35=0,0,B36/B35) -> 0 | C37: Report this in the method section
A38: Disagreements settled by tie-breaker | B38: =COUNTIFS('Screening Log'!$K$2:$K$1046,"<>Pending",'Screening Log'!$G$2:$G$1046,"Exclude",'Screening Log'!$H$2:$H$1046,"<>Exclude",'Screening Log'!$H$2:$H$1046,"<>")+COUNTIFS('Screening Log'!$K$2:$K$1046,"<>Pending",'Screening Log'!$H$2:$H$1046,"Exclude",'Screening Log'!$G$2:$G$1046,"<>Exclude",'Screening Log'!$G$2:$G$1046,"<>") -> 0
A39: Workload
A40: Pair 1 (Saif, Naif): records in set | B40: =COUNTIFS('Screening Log'!$A$2:$A$1046,"<>",'Screening Log'!$E$2:$E$1046,"<>Snowballing",'Screening Log'!$E$2:$E$1046,"<>Other sources",'Screening Log'!$F$2:$F$1046,"Pair 1") -> 348
A41: Pair 2 (Sarim, Hassan): records in set | B41: =COUNTIFS('Screening Log'!$A$2:$A$1046,"<>",'Screening Log'!$E$2:$E$1046,"<>Snowballing",'Screening Log'!$E$2:$E$1046,"<>Other sources",'Screening Log'!$F$2:$F$1046,"Pair 2") -> 348
A42: Pair 3 (Khalid, Abdullah): records in set | B42: =COUNTIFS('Screening Log'!$A$2:$A$1046,"<>",'Screening Log'!$E$2:$E$1046,"<>Snowballing",'Screening Log'!$E$2:$E$1046,"<>Other sources",'Screening Log'!$F$2:$F$1046,"Pair 3") -> 348
A43: Full-text papers: Saif | B43: =COUNTIFS('Screening Log'!$L$2:$L$1046,"Saif") -> 0
A44: Full-text papers: Naif | B44: =COUNTIFS('Screening Log'!$L$2:$L$1046,"Naif") -> 0
A45: Full-text papers: Sarim | B45: =COUNTIFS('Screening Log'!$L$2:$L$1046,"Sarim") -> 0
A46: Full-text papers: Hassan | B46: =COUNTIFS('Screening Log'!$L$2:$L$1046,"Hassan") -> 0
A47: Full-text papers: Khalid | B47: =COUNTIFS('Screening Log'!$L$2:$L$1046,"Khalid") -> 0
A48: Full-text papers: Abdullah | B48: =COUNTIFS('Screening Log'!$L$2:$L$1046,"Abdullah") -> 0
A49: Checks
A50: Screening Log rows match records to screen | B50: =IF(B9="","Waiting for duplicate count",IF(B12=B10,"OK","Mismatch: "&B12&" rows vs "&B10&" expected")) -> OK
A51: Every record assigned to a pair | B51: =IF(COUNTIFS('Screening Log'!$A$2:$A$1046,"<>",'Screening Log'!$E$2:$E$1046,"<>Snowballing",'Screening Log'!$E$2:$E$1046,"<>Other sources",'Screening Log'!$F$2:$F$1046,"")=0,"OK",COUNTIFS('Screening Log'!$A$2:$A$1046,"<>",'Screening Log'!$E$2:$E$1046,"<>Snowballing",'Screening Log'!$E$2:$E$1046,"<>Other sources",'Screening Log'!$F$2:$F$1046,"")&" record(s) with no pair") -> OK
A52: Both screeners finished | B52: =IF(COUNTIFS('Screening Log'!$A$2:$A$1046,"<>",'Screening Log'!$E$2:$E$1046,"<>Snowballing",'Screening Log'!$E$2:$E$1046,"<>Other sources",'Screening Log'!$K$2:$K$1046,"Waiting")=0,"OK",COUNTIFS('Screening Log'!$A$2:$A$1046,"<>",'Screening Log'!$E$2:$E$1046,"<>Snowballing",'Screening Log'!$E$2:$E$1046,"<>Other sources",'Screening Log'!$K$2:$K$1046,"Waiting")&" record(s) still need a second decision") -> OK
A53: No unresolved disagreements | B53: =IF(COUNTIFS('Screening Log'!$K$2:$K$1046,"Pending")=0,"OK",COUNTIFS('Screening Log'!$K$2:$K$1046,"Pending")&" pending: tie-breaker to resolve") -> OK
A54: Every full-text exclusion has a code | B54: =IF(COUNTIFS('Screening Log'!$N$2:$N$1046,"Exclude",'Screening Log'!$O$2:$O$1046,"")=0,"OK",COUNTIFS('Screening Log'!$N$2:$N$1046,"Exclude",'Screening Log'!$O$2:$O$1046,"")&" exclusion(s) missing a code") -> OK
A55: Every full-text paper has a reader | B55: =IF(COUNTIFS('Screening Log'!$A$2:$A$1046,"<>",'Screening Log'!$E$2:$E$1046,"<>Snowballing",'Screening Log'!$E$2:$E$1046,"<>Other sources",'Screening Log'!$K$2:$K$1046,"Include",'Screening Log'!$L$2:$L$1046,"")+COUNTIFS('Screening Log'!$A$2:$A$1046,"<>",'Screening Log'!$E$2:$E$1046,"<>Snowballing",'Screening Log'!$E$2:$E$1046,"<>Other sources",'Screening Log'!$K$2:$K$1046,"Maybe",'Screening Log'!$L$2:$L$1046,"")+SUM(COUNTIFS('Screening Log'!$A$2:$A$1046,"<>",'Screening Log'!$E$2:$E$1046,{"Snowballing","Other sources"},'Screening Log'!$L$2:$L$1046,""))=0,"OK",COUNTIFS('Screening Log'!$A$2:$A$1046,"<>",'Screening Log'!$E$2:$E$1046,"<>Snowballing",'Screening Log'!$E$2:$E$1046,"<>Other sources",'Screening Log'!$K$2:$K$1046,"Include",'Screening Log'!$L$2:$L$1046,"")+COUNTIFS('Screening Log'!$A$2:$A$1046,"<>",'Screening Log'!$E$2:$E$1046,"<>Snowballing",'Screening Log'!$E$2:$E$1046,"<>Other sources",'Screening Log'!$K$2:$K$1046,"Maybe",'Screening Log'!$L$2:$L$1046,"")+SUM(COUNTIFS('Screening Log'!$A$2:$A$1046,"<>",'Screening Log'!$E$2:$E$1046,{"Snowballing","Other sources"},'Screening Log'!$L$2:$L$1046,""))&" paper(s) with no reader") -> 1 paper(s) with no reader

Sheet Lists
A1: Exclusion code | B1: Meaning (from protocol) | D1: Sources | E1: People | F1: Pair | G1: Screener 1 | H1: Screener 2 | I1: Database | J1: Synthesis
A2: E1 | B2: Other privacy technique only, no homomorphic encryption (hybrids with HE are kept) | D2: IEEE Xplore | E2: Saif | F2: Pair 1 | G2: Saif | H2: Naif | I2: IEEE Xplore | J2: RQ1, RQ4
A3: E2 | B3: Not applied to health data | D3: PubMed | E3: Naif | F3: Pair 2 | G3: Sarim | H3: Hassan | I3: PubMed | J3: RQ3
A4: E3 | B4: Purely theoretical, no implementation or results | D4: Scopus | E4: Sarim | F4: Pair 3 | G4: Khalid | H4: Abdullah | I4: Scopus | J4: RQ2
A5: E4 | B5: Survey, review, editorial, poster abstract, or thesis | D5: Snowballing | E5: Hassan
A6: E5 | B6: Full text not available through UDST library (use 'Full text retrieved?' = No) | D6: Other sources | E6: Khalid
A7: E6 | B7: Duplicate or earlier version of an included study | E7: Abdullah

Sheet Search Log
A1: Database | B1: Pair | C1: Run by | D1: Confirmed by | E1: Date run | F1: Exact string used | G1: Filters applied | H1: Results | I1: Notes / changes
A2: IEEE Xplore | B2: Pair 1 | C2: Saif | D2: Naif | E2: 46305 | F2: ("Abstract":"homomorphic encryption" OR "Abstract":"fully homomorphic" OR "Abstract":FHE OR "Abstract":CKKS OR "Abstract":BFV OR "Abstract":BGV OR "Abstract":TenSEAL OR "Abstract":"Microsoft SEAL") AND ("Abstract":"machine learning" OR "Abstract":"logistic regression" OR "Abstract":"neural network" OR "Abstract":"deep learning" OR "Abstract":classif* OR "Abstract":predict* OR "Abstract":inference) AND ("Abstract":health* OR "Abstract":medical OR "Abstract":clinical OR "Abstract":patient* OR "Abstract":disease* OR "Abstract":biomedical OR "Abstract":diagnos* OR "Abstract":genom* OR "Abstract":cancer OR "Abstract":diabet* OR "Abstract":"heart disease" OR "Abstract":cardiovascular) | G2: Publication Year 2016–2026; Conferences and Journals | H2: 337 | I2: Exported in 4 RIS files (100 + 100 + 100 + 37): research/slr/exports/IEEE_2026-10-10_p1–p4.ris
A3: PubMed | B3: Pair 2 | C3: Sarim | D3: Hassan | E3: 46305 | F3: ("homomorphic encryption"[tiab] OR "fully homomorphic"[tiab] OR FHE[tiab] OR CKKS[tiab] OR BFV[tiab] OR BGV[tiab] OR TenSEAL[tiab] OR "Microsoft SEAL"[tiab]) AND ("machine learning"[tiab] OR "logistic regression"[tiab] OR "neural network"[tiab] OR "deep learning"[tiab] OR classif*[tiab] OR predict*[tiab] OR inference[tiab]) AND (health*[tiab] OR medical[tiab] OR biomedical[tiab] OR clinical[tiab] OR patient*[tiab] OR disease*[tiab] OR diagnos*[tiab] OR genom*[tiab] OR cancer[tiab] OR diabet*[tiab] OR "heart disease"[tiab] OR cardiovascular[tiab]) AND 2016:2026[dp] AND english[la] | G3: In the string: 2016:2026[dp], english[la] | H3: 172 | I3: Replaces ACM Digital Library (no UDST subscription; filters and export locked). A [tw] variant (176 results) was tested and not used. Export: research/slr/exports/PubMed_2026-10-10.nbib
A4: Scopus | B4: Pair 3 | C4: Khalid | D4: Abdullah | E4: 46305 | F4: TITLE-ABS-KEY ( "homomorphic encryption" OR "fully homomorphic" OR fhe OR ckks OR bfv OR bgv OR tenseal OR "Microsoft SEAL" ) AND TITLE-ABS-KEY ( "machine learning" OR "logistic regression" OR "neural network" OR "deep learning" OR classif* OR predict* OR inference ) AND TITLE-ABS-KEY ( health* OR medical OR biomedical OR clinical OR patient* OR disease* OR diagnos* OR genom* OR cancer OR diabet* OR "heart disease" OR cardiovascular ) AND PUBYEAR > 2015 AND PUBYEAR < 2027 AND LANGUAGE ( english ) AND ( DOCTYPE ( ar ) OR DOCTYPE ( cp ) ) | G4: In the string: PUBYEAR 2016–2026, English, DOCTYPE ar + cp | H4: 1017 | I4: Over the 400 limit. Narrowing was tested (766 and 855 results, still over), so the full 1,017 was kept by team decision. Export: research/slr/exports/Scopus_2026-10-10.ris
A5: Total identified | H5: =SUM(H2:H4) -> 1526

Sheet Screening Log
A1: Record ID | B1: Title | C1: Authors | D1: Year | E1: Source | F1: Pair | G1: Screener 1 decision | H1: Screener 2 decision | I1: Agree? | J1: Resolved decision | K1: Final T/A | L1: Full-text reader | M1: Full text retrieved? | N1: Full-text decision | O1: Exclusion code | P1: Notes | Q1: Abstract
A2: R0001 | B2: Research on Crt-Based Paillier Encryption Optimization Methods | C2: Pan, S.; Liu, Y.; Hu, X.; Zhu, J. | D2: 2025 | E2: Scopus | F2: Pair 1 | I2: =IF(OR(G2="",H2=""),"",IF(G2=H2,"Yes","No")) | K2: =IF(OR(E2="Snowballing",E2="Other sources"),"n/a",IF(AND(G2="",H2=""),"",IF(OR(G2="",H2=""),"Waiting",IF(G2=H2,G2,IF(AND(G2<>"Exclude",H2<>"Exclude"),"Maybe",IF(J2<>"",J2,"Pending")))))) | P2: Found in: Scopus; IEEE · DOI: 10.1109/CISP-BMEI68103.2025.11259311 | Q2: With the increasing demands for privacy protection in cross-domain medical coordination and related fields, the Paillier homomorphic encryption algorithm has garnered significant attention as a foundational technology for data privacy preservation. In large-scale data scenarios such as disease prediction models in major hospitals, cross-bank financial risk prediction, and inter-regional health monitoring statistics, substantial ciphertext computations are required. Consequently, traditional Paillier schemes encounter the following limitations. To enhance encryption computational performance, this paper proposes a multi-prime decomposition-based Paillier scheme that overcomes the deficiency of existing optimization methods being solely applicable to decryption procedures. The advantage lies in parallelizing the two primary modular exponentiation operations gm and in Rn the encryption process without algorithmic modifications, subsequently computing the final ciphertext through an improved CRT construction algorithm. The technical implementation adopts a staged reconstruction mechanism to mitigate overflow risks in large-number arithmetic, incorporating cryptographically secure random number generation and balanced prime allocation strategies to ensure coordinated unification between computational load and security strength. Algorithmic analysis demonstrates that under sufficient parallel conditions, near-linear acceleration performance can be achieved. Experimental validation shows that our method achieves 2-4 × performance improvement under 2048-bit key configurations, providing efficient cryptographic support for practical deployments such as medical federated learning and secure multi-party computation. © 2025 IEEE.
A3: R0002 | B3: Privacy and Security Concerns in Generative AI: A Comprehensive Survey | C3: Golda, A.; Mekonen, K.; Pandey, A.; Singh, A.; Hassija, V.; Chamola, V.; Sikdar, B. | D3: 2024 | E3: Scopus | F3: Pair 2 | I3: =IF(OR(G3="",H3=""),"",IF(G3=H3,"Yes","No")) | K3: =IF(OR(E3="Snowballing",E3="Other sources"),"n/a",IF(AND(G3="",H3=""),"",IF(OR(G3="",H3=""),"Waiting",IF(G3=H3,G3,IF(AND(G3<>"Exclude",H3<>"Exclude"),"Maybe",IF(J3<>"",J3,"Pending")))))) | P3: Found in: Scopus · DOI: 10.1109/ACCESS.2024.3381611 | Q3: Generative Artificial Intelligence (GAI) has sparked a transformative wave across various domains, including machine learning, healthcare, business, and entertainment, owing to its remarkable ability to generate lifelike data. This comprehensive survey offers a meticulous examination of the privacy and security challenges inherent to GAI. It provides five pivotal perspectives essential for a comprehensive understanding of these intricacies. The paper encompasses discussions on GAI architectures, diverse generative model types, practical applications, and recent advancements within the field. In addition, it highlights current security strategies and proposes sustainable solutions, emphasizing user, developer, institutional, and policymaker involvement. © 2013 IEEE.
A4: R0003 | B4: A privacy-preserving expert system for collaborative medical diagnosis across multiple institutions using federated learning | C4: Markkandan, S.; Bhavani, N.P.G.; Nath, S.S. | D4: 2024 | E4: Scopus | F4: Pair 3 | I4: =IF(OR(G4="",H4=""),"",IF(G4=H4,"Yes","No")) | K4: =IF(OR(E4="Snowballing",E4="Other sources"),"n/a",IF(AND(G4="",H4=""),"",IF(OR(G4="",H4=""),"Waiting",IF(G4=H4,G4,IF(AND(G4<>"Exclude",H4<>"Exclude"),"Maybe",IF(J4<>"",J4,"Pending")))))) | P4: Found in: Scopus; PubMed · DOI: 10.1038/s41598-024-73334-7 · PMID: 39333305 | Q4: Expert system recommendation assists the healthcare system to develop in real-time monitoring and diagnosis of patient conditions over several healthcare institutions. Privacy concerns, however, present significant problems since patient data leaks can lead to big effects including financial losses for hospitals and invasions of personal privacy for people. To address these issues, the research introduces a privacy-preserving collaborative medical diagnosis (CMD) method on a federated learning (FL). FL maintains patient privacy and data localization by spreading only model parameters, therefore enabling training models on remote datasets. The combination of Partially Homomorphic Cryptosystem (PHC) and Residual Learning based Deep Belief Network (RDBN) ensures an accurate and safe classification of patient physiological data. Experimental results show that the proposed method is successful in maintaining the diagnostic accuracy over numerous healthcare institutions and protecting privacy. The results show that the RDBN and PHC computations requires around 1000 ms and 150 ms, respectively for classification and privacy; the data transmission from the user to server and from server to user is 5 MB and 4 MB, respectively. Finally with a 30% reduction in overhead, the proposed approach offers an average increase in classification accuracy of 10% over multiple datasets. © The Author(s) 2024.
A5: R0004 | B5: Privacy-preserving Paralinguistic Tasks | C5: Teixeira, F.; Abad, A.; Trancoso, I. | D5: 2019 | E5: Scopus | F5: Pair 1 | I5: =IF(OR(G5="",H5=""),"",IF(G5=H5,"Yes","No")) | K5: =IF(OR(E5="Snowballing",E5="Other sources"),"n/a",IF(AND(G5="",H5=""),"",IF(OR(G5="",H5=""),"Waiting",IF(G5=H5,G5,IF(AND(G5<>"Exclude",H5<>"Exclude"),"Maybe",IF(J5<>"",J5,"Pending")))))) | P5: Found in: Scopus; IEEE · DOI: 10.1109/ICASSP.2019.8683595 | Q5: Speech is one of the primary means of communication for humans. It can be viewed as a carrier for information on several levels as it conveys not only the meaning and intention predetermined by a speaker, but also paralinguistic and extralinguistic information about the speaker's age, gender, personality, emotional state, health state and affect. This makes it a particularly sensitive biometric, that should be protected. In this work we intent to explore how Leveled Homomorphic Encryption can be combined with a Neural Network to create a privacy-preserving machine learning framework for speech-based health-related tasks. In particular, we will apply this framework to the detection and assessment of a Cold, Depression and Parkinson's Disease. Moreover, we will show how using a Quantized Neural Network, with discretized weights, allows us to apply a Leveled Homomorphic Encryption technique called batching that can be utilized to reduce the effective computational cost of this framework. © 2019 IEEE.
A6: R0005 | B6: Federated Learning for Accurate Labeling of Chest X-Ray Scans | C6: Ram, S.; Kiran, Y.N.; Bhute, A.; Khare, T. | D6: 2024 | E6: Scopus | F6: Pair 2 | I6: =IF(OR(G6="",H6=""),"",IF(G6=H6,"Yes","No")) | K6: =IF(OR(E6="Snowballing",E6="Other sources"),"n/a",IF(AND(G6="",H6=""),"",IF(OR(G6="",H6=""),"Waiting",IF(G6=H6,G6,IF(AND(G6<>"Exclude",H6<>"Exclude"),"Maybe",IF(J6<>"",J6,"Pending")))))) | P6: Found in: Scopus; IEEE · DOI: 10.23919/FRUCT64283.2024.10749865 | Q6: Federated learning is an increasingly common technique used within machine learning that allows multiple devices to collectively train a model without necessitating the centralization of data. This approach is highly valuable within medical tasks, where privacy concerns within patient datasets can be mitigated through the decentralization of machine learning training. Within past literature, there have remained difficulties in constructing well annotated, large chest X-ray datasets due to these patient privacy concerns. In this paper, we seek to demonstrate the validity of federated learning by training a deep learning model on decentralized Chest X-ray imaging data. We utilize the publicly available NIH Chest X-ray dataset to train our model. Five clients were trained over 10 rounds, and a ResNet-34 global model was initialized and moved to a GPU, where clients iterated over each round to update the model. We initialized a new parameter accumulation dictionary for each round that was outfitted with Secure Aggregation algorithm with in-built additive homomorphic encryption of local parameters towards parameter averaging. The model achieved a validation loss of 0.09 and an accuracy of 0.83. These results indicate that the outlined federated learning approach was able to approach benchmark clinical grade accuracy, demonstrating the effectiveness of federated learning in advanced medical imaging analysis with the preservation of patient privacy. © 2024 FRUCT Oy.
A7: R0006 | B7: Assessment of intracranial venous blood flow after subarachnoid hemorrhage: A new approach to diagnose vasospasm with transcranial color-coded duplex sonography | C7: Connolly, F.; Schreiber, S.J.; Leithner, C.; Bohner, G.; Vajkoczy, P.; Valdueza, J.M. | D7: 2018 | E7: Scopus | F7: Pair 3 | I7: =IF(OR(G7="",H7=""),"",IF(G7=H7,"Yes","No")) | K7: =IF(OR(E7="Snowballing",E7="Other sources"),"n/a",IF(AND(G7="",H7=""),"",IF(OR(G7="",H7=""),"Waiting",IF(G7=H7,G7,IF(AND(G7<>"Exclude",H7<>"Exclude"),"Maybe",IF(J7<>"",J7,"Pending")))))) | P7: Found in: Scopus; PubMed · DOI: 10.3171/2017.5.JNS17232 · PMID: 29243981 | Q7: Objective: Transcranial color-coded duplex sonography (TCCS) is a reliable tool that is used to assess vasospasm in the M1 segment of the middle cerebral artery (MCA) after subarachnoid hemorrhage (SAH). A distinct increase in blood flow velocity (BFV) is the principal criterion for vasospasm. The MCA/internal carotid artery (ICA) index (Lindegaard Index) is also widely used to distinguish between vasospasm and cerebral hyperperfusion. However, extracranial ultrasonography assessment of the neck vessels might be difficult in an intensive care unit. Therefore, the authors evaluated whether the relationship of intracranial arterial to venous BFV might indicate vasospasm with similar or even better accuracy. Methods: Patients who presented between 2008 and 2015 with aneurysmal SAH were prospectively enrolled in the study. Digital subtraction angiography (DSA) and TCCS were performed within 24 hours of each other to assess vasospasm 8.10 days after SAH. The following different TCCS parameters were analyzed to assess vasospasm in the MCA and were compared with the gold-standard DSA parameters: 1) mean time-averaged maximum BFV (Vmean) of the MCA, 2) peak systolic velocity (PSV) of the MCA, 3) the Lindegaard Index using Vmean as well as PSV, and 4) a new arteriovenous index (AVI) between the MCA and the basal vein of Rosenthal using Vmean and PSV. The best cutoff values for these parameters to distinguish vasospasm from normal perfusion or hyperperfusion were calculated using receiver operating characteristic curve analysis. Sensitivity, specificity, positive predictive value, and negative predictive value as well as the overall accuracy for each cutoff value were analyzed. Results: A total of 102 patients (mean age 52 ± 12 years) were evaluated. Bilateral MCA assessment by TCCS was successful in all patients. In 6 cases (3%), the BFV of the basal vein of Rosenthal could not be analyzed. The AVI could not be calculated in 50 of 204 cases (25%) because the insonation quality was very low in one of the ICAs. An AVI > 10 for Vmean and an AVI > 12 for systolic velocity provided the highest accuracies of 87% and 86%, respectively. Regarding the Lindegaard Index, the accuracy was highest using a threshold of > 3 for the mean BFV (84%) as well as systolic BFV (80%). BFVs in the MCA of ≥ 120 cm/sec (Vmean) and ≥ 200 cm/sec (PSV) predicted vasospasm with accuracies of 84% and 83%, respectively. A combined analysis of the MCA BFV and the AVI led to a slight increase in specificity (Vmean, 94%; PSV, 93%) and positive predictive value (Vmean, 88%; PSV 86%) without further improvement in accuracy (Vmean, 88%; PSV, 84%). Conclusions: The intracranial AVI is a reliable parameter that can be used to assess vasospasm after SAH. Its reliability for differentiating vasospasm and hyperperfusion is slightly higher than that for the established Lindegaard Index, and this method has the additional advantage of a remarkably lower failure rate. © AANS 2018.
A8: R0007 | B8: A Pervasive, Efficient and Private Future: Realizing Privacy-Preserving Machine Learning Through Hybrid Homomorphic Encryption | C8: Nguyen, K.; Budzys, M.; Frimpong, E.; Khan, T.; Michalas, A. | D8: 2024 | E8: Scopus | F8: Pair 1 | I8: =IF(OR(G8="",H8=""),"",IF(G8=H8,"Yes","No")) | K8: =IF(OR(E8="Snowballing",E8="Other sources"),"n/a",IF(AND(G8="",H8=""),"",IF(OR(G8="",H8=""),"Waiting",IF(G8=H8,G8,IF(AND(G8<>"Exclude",H8<>"Exclude"),"Maybe",IF(J8<>"",J8,"Pending")))))) | P8: Found in: Scopus; IEEE · DOI: 10.1109/DASC64200.2024.00013 | Q8: Machine Learning (ML) has become one of the most impactful fields of data science in recent years. However, a significant concern with ML is its privacy risks due to rising attacks against ML models. Privacy-Preserving Machine Learning (PPML) methods have been proposed to mitigate the privacy and security risks of ML models. A popular approach to achieving PPML uses Homomorphic Encryption (HE). However, the highly publicized inefficiencies of HE make it unsuitable for highly scalable scenarios with resource-constrained devices. Hence, Hybrid Homomorphic Encryption (HHE) - a modern encryption scheme that combines symmetric cryptography with HE - has recently been introduced to overcome these challenges. HHE potentially provides a foundation to build new efficient and privacy-preserving services that transfer expensive HE operations to the cloud. This work introduces HHE to the ML field by proposing resource-friendly PPML protocols for edge devices. More precisely, we utilize HHE as the primary building block of our PPML protocols. We assess the performance of our protocols by first extensively evaluating each party's communication and computational cost on a dummy dataset and show the efficiency of our protocols by comparing them with similar protocols implemented using plain BFV. Subsequently, we demonstrate the real-world applicability of our construction by building an actual PPML application that uses HHE as its foundation to classify heart disease based on sensitive ECG data. © 2024 IEEE.
A9: R0008 | B9: A Hybrid BiLSTM-Attention and Homomorphic Encryption Framework for Privacy-Preserving Threat Detection in Cloud Computing Environments | C9: Dyavani, N.R.; Garikipati, V.; Ubagaram, C.; Jayaprakasam, B.S.; Mandala, R.R.; Aiswarya, R.S. | D9: 2025 | E9: Scopus | F9: Pair 2 | I9: =IF(OR(G9="",H9=""),"",IF(G9=H9,"Yes","No")) | K9: =IF(OR(E9="Snowballing",E9="Other sources"),"n/a",IF(AND(G9="",H9=""),"",IF(OR(G9="",H9=""),"Waiting",IF(G9=H9,G9,IF(AND(G9<>"Exclude",H9<>"Exclude"),"Maybe",IF(J9<>"",J9,"Pending")))))) | P9: Found in: Scopus · DOI: 10.1142/S2010324725400119 | Q9: Cloud computing has become indispensable for modern digital services in healthcare, finance and education, yet its distributed and multi-tenant nature exposes it to increasingly sophisticated cyberattacks. With the anticipated integration of quantum computing into cloud infrastructures, the need for robust, privacy-preserving and fault-tolerant security mechanisms is greater than ever. Traditional threat detection models, including Convolutional Neural Networks, Support Vector Machines and Autoencoders, rely on raw or partially anonymized data, which risks user privacy and lacks the ability to effectively capture sequential dependencies in dynamic cloud traffic. To address these limitations, we propose a Hybrid BiLSTM-Attention and Homomorphic Encryption Framework for intrusion detection in cloud environments. The BiLSTM component extracts bidirectional temporal dependencies from encrypted traffic, while the attention mechanism highlights critical time steps to improve detection accuracy. Homomorphic Encryption ensures sensitive data remains encrypted throughout the detection pipeline, supporting privacy without sacrificing computational performance. Experimental results on a benchmark intrusion detection dataset demonstrate superior performance, achieving 99.28% accuracy, 99.26% precision, 99.89% recall and a 99.5% F1-score, along with a low false-negative rate (0.1%) and high AUC (0.9847). Training (1.2s) and prediction (0.2s) times confirm the framework’s suitability for real-time deployment in privacy-critical applications. Importantly, the proposed system embodies principles of fault tolerance by maintaining resilience against adversarial interference and data leakage, a requirement that closely parallels the reliability demands of emerging quantum-classical hybrid systems. This synergy between deep learning, encryption and fault tolerance provides a pathway toward secure and privacy-preserving cloud infrastructures in the quantum computing era. © 2025 World Scientific Publishing Company.
A10: R0009 | B10: Clustered Federated Learning for Healthcare Analytics: A Dual Blockchain-Functional Encryption Method for Fortified Aggregation | C10: Melhem, A.; Aleroud, A.; Al-Mamun, A.; Ibrahem, M.I. | D10: 2026 | E10: Scopus | F10: Pair 3 | I10: =IF(OR(G10="",H10=""),"",IF(G10=H10,"Yes","No")) | K10: =IF(OR(E10="Snowballing",E10="Other sources"),"n/a",IF(AND(G10="",H10=""),"",IF(OR(G10="",H10=""),"Waiting",IF(G10=H10,G10,IF(AND(G10<>"Exclude",H10<>"Exclude"),"Maybe",IF(J10<>"",J10,"Pending")))))) | P10: Found in: Scopus; IEEE · DOI: 10.1109/JIOT.2026.3658441 | Q10: The use of healthcare data for collaborative machine learning training amplifies the demand for strong privacy and security protection. Federated learning (FL) addresses this by sharing model gradients instead of raw patient data. However, FL faces critical challenges, including vulnerability to adversarial attacks (e.g., membership inference and model poisoning), reliance on centralized aggregation (introducing single points of failure), and privacy leakage risks from gradient exchanges. To overcome these limitations, we propose C2SecFL, a cross-clustered secure FL framework that combines adaptive, model-aware clustering with an inner-product functional encryption (IPFE) scheme enabling encrypted aggregation without a key distribution center (KDC). A lightweight permissioned blockchain provides tamper-evident coordination and auditability across clusters without introducing a centralized trust anchor. Experiments on diverse models show substantially lower cryptographic overhead compared to homomorphic encryption baselines. Encryption is approximately 3.6×faster, and aggregation is up to 2.2× faster, while predictive utility is preserved. Under adversarial settings with compromised participants, C2SecFL reduces the average attack success rate (ASR) by about 80% relative to a FedAvg baseline. It mitigates membership-inference risk by encrypting updates end-to-end and revealing only aggregate inner products. Our extensive experiments on a heart attack dataset demonstrate that C2SecFL provides a practical, auditable, and resilient approach to secure healthcare FL. © 2026 IEEE.
A11: R0010 | B11: A Privacy-Preserving Blockchain and Machine Learning Framework for Secure Next-Generation Genomic Data Analysis | C11: Morsi, S.A.; Husain, H.I.; Nair, R.; Alkahtani, H.; Abdulsahib, G.M.; Aldhyani, T.H.H. | D11: 2026 | E11: Scopus | F11: Pair 1 | I11: =IF(OR(G11="",H11=""),"",IF(G11=H11,"Yes","No")) | K11: =IF(OR(E11="Snowballing",E11="Other sources"),"n/a",IF(AND(G11="",H11=""),"",IF(OR(G11="",H11=""),"Waiting",IF(G11=H11,G11,IF(AND(G11<>"Exclude",H11<>"Exclude"),"Maybe",IF(J11<>"",J11,"Pending")))))) | P11: Found in: Scopus · DOI: 10.15849/ijasca.v18i1.52 | Q11: Next-generation genomic data analysis faces ongoing challenges in collaboration, privacy, and scalability. With data protection and no access control deficiency, centralized systems lack sufficient protection for sensitive genomic data. The first-of-its-kind analysis of genomics combined with integrated machine learning and homomorphic encryption with the new privacy-preserving computational framework will be revolutionary. The use of smart contracts, which is unlike other frameworks, for access control, tokenized encrypted, and suspended federated model training during the suspension of other research nodes will be unprecedented. Simulation of genomic datasets (0 Major issues were identified in file sync performance and data protection and security) Vis-a-vis the other frameworks, the Model Proposed outperformed traditional, federated and HE based frameworks with significant. Of the models proposed, this one is the most impressive with a score of 94% precision, 92% recall, 0.93 computed F1 score, and 0.96 Area Under Curve (AUC). The model with the best performance. With 5K genomic datasets in a pilot simulation, collaboration improved by 25% with no breaches in the datasets. The promise of this design to ethically and securely address privacy-preserving genomic data analysis and the subsequent use of Artificial Intelligence in biomedical systems will be groundbreaking. © Al-Zaytoonah University of Jordan (ZUJ).
A12: R0011 | B12: Cryptanalysis and Modification of a Variant of Matrix Operation for Randomization or Encryption (v-MORE) | C12: Alex, S.; Yang, B. | D12: 2025 | E12: Scopus | F12: Pair 2 | I12: =IF(OR(G12="",H12=""),"",IF(G12=H12,"Yes","No")) | K12: =IF(OR(E12="Snowballing",E12="Other sources"),"n/a",IF(AND(G12="",H12=""),"",IF(OR(G12="",H12=""),"Waiting",IF(G12=H12,G12,IF(AND(G12<>"Exclude",H12<>"Exclude"),"Maybe",IF(J12<>"",J12,"Pending")))))) | P12: Found in: Scopus · DOI: 10.1007/978-3-031-96590-6_24 | Q12: A variant of Matrix Operation for Randomization or Encryption (v-MORE) is a lightweight, real number-based, fully homomorphic encryption scheme used for outsourced secure medical data processing. This paper shows the vulnerability of v-MORE to a ciphertext-only attack when it is used in privacy-preserving applications where the data is not random. From the ciphertexts of v-MORE, the attacker can solve for its secrets based on linear algebra and predict the plaintext from a new ciphertext with 100% confidence. Hence, v-MORE can not ensure the privacy of medical data, which is not random, while processing it remotely and transmitting it over networks. Experimental analysis shows that the attack complexity is very low. v-MORE encryption is modified to mitigate the proposed ciphertext-only attack and developed additively homomorphic encryption that operates on real numbers (AHE-R). Also, experimental analysis and security analysis confirm that the modifications do not noticeably affect the computational and communication overhead while providing data security. © IFIP International Federation for Information Processing 2025.
A13: R0012 | B13: FreqLT: Frequency-Domain Linear Transformation for Privacy-Preserving and Efficient Machine Learning on Wearable Sensor Signals | C13: Li, S.; Chen, L.; Bo, Y. | D13: 2025 | E13: Scopus | F13: Pair 3 | I13: =IF(OR(G13="",H13=""),"",IF(G13=H13,"Yes","No")) | K13: =IF(OR(E13="Snowballing",E13="Other sources"),"n/a",IF(AND(G13="",H13=""),"",IF(OR(G13="",H13=""),"Waiting",IF(G13=H13,G13,IF(AND(G13<>"Exclude",H13<>"Exclude"),"Maybe",IF(J13<>"",J13,"Pending")))))) | P13: Found in: Scopus · DOI: 10.1145/3737903.3768570 | Q13: The proliferation of wearable computing devices has enabled unprecedented opportunities for personalized health monitoring and human-computer interaction. However, the continuous stream of highly sensitive physiological and kinematic data they generate poses significant privacy and security risks, especially when processed on untrusted cloud-based Machine Learning as a Service (MLaaS) platforms. Existing privacy-preserving techniques present a stark tradeoff: cryptographic methods like Homomorphic Encryption offer robust security but are computationally prohibitive for resource-constrained wearables, while simpler perturbation-based methods degrade model performance and offer weak privacy guarantees. To address this challenge, we propose FreqLT, a novel and lightweight framework for Privacy-Preserving and Efficient Machine Learning on wearable devices. The core insight of FreqLT is that the discriminative information for most sensor-based ML tasks resides in the frequency domain. It is a learnable, invertible linear transformation directly to the frequency-domain representation of the sensor data, effectively obscuring the original signal’s time-domain characteristics and sensitive statistical properties. Our experiments on different datasets show that FreqLT provides superior privacy protection compared to other methods. © 2025 Copyright held by the owner/author(s).
... A477: R0476 | B477: Confidential AI Using Homomorphic Encryption-Based Deep Learning for Secure Data Analytics | C477: Roy, J.; Sheeba, G.; Rao, S.G.; Mishra, A.; Abbas, H.M.; Al-Dulaimi, H.W.; Alhayaly, A.A. | D477: 2025 | E477: Scopus | F477: Pair 2 | I477: =IF(OR(G477="",H477=""),"",IF(G477=H477,"Yes","No")) | K477: =IF(OR(E477="Snowballing",E477="Other sources"),"n/a",IF(AND(G477="",H477=""),"",IF(OR(G477="",H477=""),"Waiting",IF(G477=H477,G477,IF(AND(G477<>"Exclude",H477<>"Exclude"),"Maybe",IF(J477<>"",J477,"Pending")))))) | P477: Found in: Scopus; IEEE · DOI: 10.1109/ICCR67387.2025.11292510 | Q477: Particularly in handling sensitive data, the growing dependence on artificial intelligence (AI) for data analytics poses serious security problems. Conventional encryption methods hinder safe AI adoption by difficulty balancing privacy with computational efficiency. This paper presents a Confidential AI framework enabling privacy-preserving data analytics by merging homomorphic encryption (HE) with deep learning. To guarantee end-to- end confidentiality, the suggested method lets encrypted data be handled straight without decryption. We create a new homomorphic encrypted deep neural network (HEDNN) minimising latency and computational overhead by optimising encrypted computations. Experimental assessments show that, on encrypted datasets, our framework achieves 85% inference accuracy while preserving a 30% decrease in processing overhead over current HE-based AI systems.These results display how feasible safe AI-driven analytics are without sacrificing performance or accuracy. Where information privateness is important, the suggested paradigm unearths tremendous makes use of in cybersecurity, banking, and healthcare. By advancing secure synthetic intelligence techniques, our paintings helps to create dependable AI systems that hold statistics confidentiality in sensible settings. © 2025 IEEE.
A478: R0477 | B478: [Front cover] | D478: 2016 | E478: IEEE Xplore | F478: Pair 3 | I478: =IF(OR(G478="",H478=""),"",IF(G478=H478,"Yes","No")) | K478: =IF(OR(E478="Snowballing",E478="Other sources"),"n/a",IF(AND(G478="",H478=""),"",IF(OR(G478="",H478=""),"Waiting",IF(G478=H478,G478,IF(AND(G478<>"Exclude",H478<>"Exclude"),"Maybe",IF(J478<>"",J478,"Pending")))))) | P478: Found in: IEEE · DOI: 10.1109/CIST.2016.7804841 | Q478: The following topics are dealt with: enterprise architecture; E-learning; finance management system; ontology; SME; drug supply; inventory management; lean-maintenance; hospital logistics; FLOSS ERP system; UTAUT2; SEM; R; vertical handover; MIH architecture; intelligence E-CRM; ITIL framework; data quality; data warehouse security; good governance monitoring; TestNG tests; UML sequence diagrams; Scrum process; health data management system; Hadoop-Agent; data mining; RIA interfaces; XML technology; Web applications; social networks; spanning tree; PSO algorithm; MDA; CIM; PIM; SoaML; IFML; supply chain demand forecasts; game theory; business process verification; intrusion detection; stateful pattern matching; neural network; big incremental dynamic case-based reasoning-multi-agents system; BIDCBR-MAS; cloud computing; EA readiness instrument; reverse engineering; Web mining; information system security risk management; object oriented programs; partitioning filter; memetic hunting search algorithm; traveling salesman problem; SYSML language; KPI; project portfolio management information systems; information entropy; PPMIS; XBRL; GUI; Java source code analysis; crowdsourcing; critical infrastructures; CCSD; TOPSIS; AprioriMin; stock market price prediction; HP filter; association rules; k-means algorithm; automatic keyphrase extraction; distributed test architecture; dictionary Al-Qamus; text summarization; sign language; community question answering; distributional semantics; feature extraction; sentiment analysis; information retrieval; Lahajat; rule-based converter; data hiding; image cropping; LSB steganography; bag of features model; sampling theory; 3D segmentation algorithms; DSWT; DCT; GPU; adaptive learning system; Bayesian network; ALS_CORR[LP]; virtual labs; intelligent tutoring systems; MOOC; metadata; recommender system; smart curriculum sequencing; software engineering learning; IDE 2.0; Moodle; university of the future; dynamic programming; traffic signal control system; PHM as a service; mobile cloud; honeypots; genetic algorithm; QFN electronic package; response surface approach; EST.Stemmer; cloud database; homomorphic encryption; interoperability; IDS-AM-Clust; O&M cost simulation; fluid-structure interaction problems; spectrum allocation; cognitive radio system; vehicle path planning problem; tube hydroforming; liquidity; wind turbine blade; air-flow; identity management systems; harmony search algorithm; SCOR model; ARIS; embedded system; Pennes bioheat equation; max-cut problem; min-conflict heuristic; AHP method; Tr-OrBAC model; Q-learning; smart cities; extended Kalman filter; evolutionary machine learning; indoor localization; particle map matching; activity recognition; back-propagation algorithm; 4th generation heterogeneous wireless network; vehicular navigation spoofing detection; 2-D DOA estimation; MUSIC algorithm; uniform circular array; smart grid; residential microgrid; signaling DoS attacks; 3G mobile networks; safety instrumented system; routing process; VANET; intelligent transportation systems; wireless sensor networks; FPGA; pipelined AES S-box; disaster emergency system; alert message dissemination protocol; LEACH protocol; metacognitive learning management system; and self-regulated learning.
A479: R0478 | B479: Brachial-ankle pulse wave velocity as a risk factor for high body fat mediated by blood pressure | C479: Wang, P.; Liao, G.; Wu, X.; Yu, R.; Ma, J. | D479: 2023 | E479: Scopus | F479: Pair 1 | I479: =IF(OR(G479="",H479=""),"",IF(G479=H479,"Yes","No")) | K479: =IF(OR(E479="Snowballing",E479="Other sources"),"n/a",IF(AND(G479="",H479=""),"",IF(OR(G479="",H479=""),"Waiting",IF(G479=H479,G479,IF(AND(G479<>"Exclude",H479<>"Exclude"),"Maybe",IF(J479<>"",J479,"Pending")))))) | P479: Found in: Scopus; PubMed · DOI: 10.1080/10641963.2023.2197568 · PMID: 37013932 | Q479: Background: Brachial-ankle pulse wave velocity (baPWV) is an important clinical indicator of aortic stiffness and a risk predictor of cardiovascular disease and associated with obesity. However, whether body mass index (BMI) is associated with baPWV remains controversial. In our study, body fat-related indicators, including BMI, body fat rate (BFR), body fat volume (BFV), waist circumference (WC) were examined from healthy volunteers. We investigated the correlation of baPWV with these indicators and also assessed whether baPWV has the potential to predict these indicators. Methods: A total of 429 healthy participants were enrolled in this study. Body fat indices, blood pressures, baPWV and blood metabolic indices were measured and recorded. The association of baPWV and indices reflecting body fat and blood pressure, as well as mediation effect were analyzed. Results: Three different types of baPWV values were significantly correlated. Mean level of baPWV was an independent risk factor for WC, BMI, BFR, and BFV (exp(β) = 1.011, 1.004, 1.010 and 1.009, respectively, P <.001 for all) but not BMR. As for mediation effects, baPWV positively influenced WC (Total effect = 0.011, P <.001), BMI (Total effect = 0.004, P <.001) and BFV (Total effect = 0.009, P <.001) in indirect way mediated by SBP and DBP, while baPWV influenced BFR in both direct (Effect = 0.004, P =.018) and indirect way. Conclusions: Levels of baPWV correlated with obesity and is an independent risk factor for WC, BMI, BFR and BFV. Besides, baPWV positively associated with WC, BMI and BFV mainly in indirect way mediated by SBP and DBP, and baPWV associated with BFR in both direct and indirect way. © 2023 The Author(s). Published with license by Taylor & Francis Group, LLC.
A480: R0479 | B480: MFSA: Migration flamingo search algorithm based trust aware multi-party data sharing in blockchain using hierarchical homomorphic encryption | C480: Lakshmi, T.S.; Jayamangala, H. | D480: 2025 | E480: Scopus | F480: Pair 2 | I480: =IF(OR(G480="",H480=""),"",IF(G480=H480,"Yes","No")) | K480: =IF(OR(E480="Snowballing",E480="Other sources"),"n/a",IF(AND(G480="",H480=""),"",IF(OR(G480="",H480=""),"Waiting",IF(G480=H480,G480,IF(AND(G480<>"Exclude",H480<>"Exclude"),"Maybe",IF(J480<>"",J480,"Pending")))))) | P480: Found in: Scopus · DOI: 10.1177/18724981251317969 | Q480: With the exponential growth of network technology, data sharing becomes more popular and various scholars have carried out comprehensive researches for promoting its development. Multi-party data sharing generally involves multiple participants to access and share data in a trustless environment. To gain the trust of users, it is significant to provide security guarantees that protect user's privacy and obstruct unauthorized access. Therefore, it is essential to guarantee the integrity, confidentiality and trustability of sensitive data and to overcome the risks associated with malicious attacks and unauthorized access. To bridge this gap, this research introduces Migration Flamingo Search Algorithm (MFSA) for multi-party data sharing in the blockchain using hierarchical homomorphic encryption. Initially, data owner (DO) submits a file to cloud through the smart contract (SC). Thereafter, encryption of data files is done employing Hierarchical Multipart Homomorphic Encryption (HMHE). Here, Hierarchical Squeeze Forward Fractional Net (HiSqFFNet) is employed to generate hierarchical key. HiSqFFNet is introduced by combining of Hierarchical Deep Learning Neural Network (HiDeNN) with SqueezeNet. After encryption, an encrypted data is stored in Interplanetary File Systems (IPFS). Then, access request is sent by a data requester (DR) for accessing an encrypted data. The trust manager evaluates trustability of DR and the process is accomplished using MFSA that is presented by incorporating Migration Algorithm (MA) with Flamingo Search Algorithm (FSA). If the trust is acceptable, data from IPFS is decrypted and then, file is delivered to DR. The proposed MFSA is assessed with different evaluation metrics and the evaluation is done using heart disease dataset. Additionally, MFSA has obtained minimal decryption time of 10.548sec, encryption time of 7.978sec, key complexity of 0.727, time complexity of 0.455sec for 100 kb data size with key size = 64. © The Author(s) 2025
A481: R0480 | B481: Preserving Privacy in Healthcare Analytics: Federated Learning for Breast Cancer Prediction in a Collaborative Learning Framework | C481: Anuvarshini, G.B.; Varshaa, D.; Sujithra, M.; Devi, D.S. | D481: 2024 | E481: Scopus | F481: Pair 3 | I481: =IF(OR(G481="",H481=""),"",IF(G481=H481,"Yes","No")) | K481: =IF(OR(E481="Snowballing",E481="Other sources"),"n/a",IF(AND(G481="",H481=""),"",IF(OR(G481="",H481=""),"Waiting",IF(G481=H481,G481,IF(AND(G481<>"Exclude",H481<>"Exclude"),"Maybe",IF(J481<>"",J481,"Pending")))))) | P481: Found in: Scopus | Q481: Federated learning has emerged as a promising technique in machine learning, enabling collaborative training across distributed datasets. Particularly in fields like healthcare, where data privacy is paramount, federated learning offers a means to improve privacy and security. This paper addresses the critical need for safeguarding sensitive medical data by proposing a privacy-preserving federated learning algorithm. Leveraging homomorphic encryption, the proposed algorithm ensures that the learning process protects both data and model integrity. By employing a secure multi-party computation protocol, the algorithm defends against potential adversaries seeking to compromise the deep learning model. Evaluation on real-world medical datasets demonstrates the effectiveness of the approach in preserving privacy and security amidst collaborative learning environments. © Grenze Scientific Society, 2024.
A482: R0481 | B482: Reliability of State-of-Health of the Flexible Li-Ion Batteries Under Various Flexing Conditions and Calendar Aging | C482: Lall, P.; Jang, H. | D482: 2023 | E482: Scopus | F482: Pair 1 | I482: =IF(OR(G482="",H482=""),"",IF(G482=H482,"Yes","No")) | K482: =IF(OR(E482="Snowballing",E482="Other sources"),"n/a",IF(AND(G482="",H482=""),"",IF(OR(G482="",H482=""),"Waiting",IF(G482=H482,G482,IF(AND(G482<>"Exclude",H482<>"Exclude"),"Maybe",IF(J482<>"",J482,"Pending")))))) | P482: Found in: Scopus · DOI: 10.1115/1.4056412 | Q482: Due to the necessity for flexibility without compromising the Li-ion battery (LIB) state of health (SOH), LIB is a critical challenge for flexible hybrid electronic (FHE) devices. A thin form factor-based LIB with a thickness of less than 1 mm is regarded as the candidate material to suit such demands since it can be folded, bent, and twisted with minimal performance loss. Furthermore, LIB has high specific power (W/Kg) and specific energy (Wh/Kg), as well as a smaller memory effect, making it more appealing for wearable applications. While much research has been done on the chemo-physical effects of repeated charging and discharging LIB, such as solid electrolyte interphase (SEI) development, material deterioration, and so on, but such impacts owing to repeated flexure LIB have not been much studied. The deterioration of the reliability of thin-flexible power sources was investigated in this work under twist, flexing, and flex-to-install to simulate stresses of daily motions of the human body by utilizing motion-control setups in a lab setting. Furthermore, an AI-based regression model has been developed to forecast the SOH of the battery based on many variables such as physical, atmospheric, and chemo-mechanical experimental circumstances that may be difficult to address by manpower. Based on the various variables and their interactions, the generated models are expected to be used to predict battery life and assess the acceleration factors between test circumstances and usage conditions for a range of test scenarios. © 2023 by ASME.
A483: R0482 | B483: Towards Practical Secure Privacy-Preserving Machine (Deep) Learning with Distributed Data | C483: Kumar, M.; Moser, B.; Fischer, L.; Freudenthaler, B. | D483: 2022 | E483: Scopus | F483: Pair 2 | I483: =IF(OR(G483="",H483=""),"",IF(G483=H483,"Yes","No")) | K483: =IF(OR(E483="Snowballing",E483="Other sources"),"n/a",IF(AND(G483="",H483=""),"",IF(OR(G483="",H483=""),"Waiting",IF(G483=H483,G483,IF(AND(G483<>"Exclude",H483<>"Exclude"),"Maybe",IF(J483<>"",J483,"Pending")))))) | P483: Found in: Scopus · DOI: 10.1007/978-3-031-14343-4_6 | Q483: A methodology for practical secure privacy-preserving distributed machine (deep) learning is proposed via addressing the core issues of fully homomorphic encryption, differential privacy, and scalable fast machine learning. Considering that private data is distributed and the training data may contain directly or indirectly an information about private data, an architecture and a methodology are suggested for 1.mitigating the impracticality issue of fully homomorphic encryption (arising from large computational overhead) via very fast gate-by-gate bootstrapping and introducing a learning scheme that requires homomorphic computation of only efficient-to-evaluate functions;2.addressing the privacy-accuracy tradeoff issue of differential privacy via optimizing the noise adding mechanism;3.defining an information theoretic measure of privacy-leakage for the design and analysis of privacy-preserving schemes; and4.addressing the optimal model size determination issue and computationally fast training issue of scalable and fast machine (deep) learning with an alternative approach based on variational learning. A biomedical application example is provided to demonstrate the application potential of the proposed methodology. © 2022, The Author(s), under exclusive license to Springer Nature Switzerland AG.
A484: R0483 | B484: Privacy-Aware Hierarchical Federated Learning in Healthcare: Integrating Differential Privacy and Secure Multi-Party Computation | C484: Singh, J.P.; Aqsa, A.; Ghani, I.; Sonani, R.; Govindarajan, V. | D484: 2025 | E484: Scopus | F484: Pair 3 | I484: =IF(OR(G484="",H484=""),"",IF(G484=H484,"Yes","No")) | K484: =IF(OR(E484="Snowballing",E484="Other sources"),"n/a",IF(AND(G484="",H484=""),"",IF(OR(G484="",H484=""),"Waiting",IF(G484=H484,G484,IF(AND(G484<>"Exclude",H484<>"Exclude"),"Maybe",IF(J484<>"",J484,"Pending")))))) | P484: Found in: Scopus · DOI: 10.3390/fi17080345 | Q484: The development of big data analytics in healthcare has created a demand for privacy-conscious and scalable machine learning algorithms that can allow the use of patient information across different healthcare organizations. In this study, the difficulties that come with traditional federated learning frameworks in healthcare sectors, such as scalability, computational effectiveness, and preserving patient privacy for numerous healthcare systems, are discussed. In this work, a new conceptual model known as Hierarchical Federated Learning (HFL) for large, integrated healthcare organizations that include several institutions is proposed. The first level of aggregation forms regional centers where local updates are first collected and then sent to the second level of aggregation to form the global update, thus reducing the message-passing traffic and improving the scalability of the HFL architecture. Furthermore, the HFL framework leveraged more robust privacy characteristics such as Local Differential Privacy (LDP), Gaussian Differential Privacy (GDP), Secure Multi-Party Computation (SMPC) and Homomorphic Encryption (HE). In addition, a Novel Aggregated Gradient Perturbation Mechanism is presented to alleviate noise in model updates and maintain privacy and utility. The performance of the proposed HFL framework is evaluated on real-life healthcare datasets and an artificial dataset created using Generative Adversarial Networks (GANs), showing that the proposed HFL framework is better than other methods. Our approach provided an accuracy of around 97% and 30% less privacy leakage compared to the existing models of FLBM-IoT and PPFLB. The proposed HFL approach can help to find the optimal balance between privacy and model performance, which is crucial for healthcare applications and scalable and secure solutions. © 2025 by the authors.
A485: R0484 | B485: Blockchain-Based Secure and Efficient Federated Learning Scheme for IoMT Consumer Electronics Devices | C485: Xue, Y.; Zhai, Y.; Qiao, Y.; Zhang, D.; Ghoneim, A. | D485: 2026 | E485: Scopus | F485: Pair 1 | I485: =IF(OR(G485="",H485=""),"",IF(G485=H485,"Yes","No")) | K485: =IF(OR(E485="Snowballing",E485="Other sources"),"n/a",IF(AND(G485="",H485=""),"",IF(OR(G485="",H485=""),"Waiting",IF(G485=H485,G485,IF(AND(G485<>"Exclude",H485<>"Exclude"),"Maybe",IF(J485<>"",J485,"Pending")))))) | P485: Found in: Scopus · DOI: 10.1109/TCE.2026.3696410 | Q485: The Internet of Medical Things consumer electronics (IoMT-CE) devices integrated with deep learning (DL) model have achieved remarkable success in the medical field, which provides intelligent diagnostic assistance. However, as DL technologies evolve rapidly, a key challenge lies in how to continuously enhance the intelligent assisted diagnostic capabilities of IoMT-CE devices. Federated learning (FL), an effective distributed learning framework, holds great potential to address this issue. In this article, we propose a novel secure and efficient FL scheme for IoMT-CE devices based on consortium blockchain. In this scheme, all participating hospitals, the aggregation server (AS), and the noise parameter server (NPS) establish a consortium blockchain, where hash values and signature data are stored. Paillier homomorphic encryption (HE) and noise mechanisms are employed to protect patient privacy, while an elliptic curve cryptography-based proxy re-encryption (ECC-PRE) strategy is adopted to ensure model security between the AS and IoMT-CE devices. Furthermore, this scheme guarantees that model updates are applied correctly, even when local models cannot be uploaded to hospitals. Finally, the performance of our proposed scheme is verified. The results demonstrate that the encryption mechanisms have almost no impact on model accuracy, and the proposed scheme proves to be robust and fault-tolerant in cases of disconnection. © 1975-2011 IEEE.
A486: R0485 | B486: Privacy-Preserving Computing Scheme for Ciphertext Neural Network Training Based on Homomorphic Encryption | C486: Yang, S.; Li, X.; Zhang, J. | D486: 2024 | E486: Scopus | F486: Pair 2 | I486: =IF(OR(G486="",H486=""),"",IF(G486=H486,"Yes","No")) | K486: =IF(OR(E486="Snowballing",E486="Other sources"),"n/a",IF(AND(G486="",H486=""),"",IF(OR(G486="",H486=""),"Waiting",IF(G486=H486,G486,IF(AND(G486<>"Exclude",H486<>"Exclude"),"Maybe",IF(J486<>"",J486,"Pending")))))) | P486: Found in: Scopus · DOI: 10.1145/3673277.3673303 | Q486: With the rapid development of artificial intelligence, privacy protection of AI is critical for prediction and training on sensitive data. A novel scheme is presented for privacy-preserving neural network training based on homomorphic encryption. As neural network is trained in ciphertext, the nonlinear activation function has to be polynomial approximated for computation with arithmetic operations. A new method is proposed to the nonlinear activation function approximation using a generalized Lagrange interpolation formula for derivatives. By selecting proper interpolation points, the general forms of the mainstream activation functions are derived. The proposed scheme is evaluated using a sensitive medical dataset, demonstrating its practicality in speed and computational complexity. Experimental results show that this scheme effectively addresses the polynomial approximation problem of the activation function in ciphertext neural network training. It maintains the computability of ciphertext data while ensuring data privacy, improves the accuracy of ciphertext training, and reduces the mean square error. Meanwhile, the feasibility of training deeper ciphertext deep neural networks is verified. This scheme provides practical support for mainstream learning models, such as logistic regression and multi-layer neural networks. © 2024 Copyright held by the owner/author(s).
A487: R0486 | B487: Efficient Data Transfer in Internet of Things (IoT) Networks: Privacy-Preserving Techniques for Edge-Cloud Collaborative Computing in Resource-Limited Settings | C487: Sivaraman, K.; Kottur, S.; Rekha, M.; Shobana, D.; Karthikeyan, G.; Mohandoss, S. | D487: 2026 | E487: Scopus | F487: Pair 3 | I487: =IF(OR(G487="",H487=""),"",IF(G487=H487,"Yes","No")) | K487: =IF(OR(E487="Snowballing",E487="Other sources"),"n/a",IF(AND(G487="",H487=""),"",IF(OR(G487="",H487=""),"Waiting",IF(G487=H487,G487,IF(AND(G487<>"Exclude",H487<>"Exclude"),"Maybe",IF(J487<>"",J487,"Pending")))))) | P487: Found in: Scopus; IEEE · DOI: 10.1109/ICSFT66733.2026.11506847 | Q487: It has never been seen before that opportunities for data-driven automation, monitoring, and intelligent decision-making have evolved as a result of the rapid proliferation of ecosystems that are connected to the Internet of Things (IoT). The adoption of the Internet of Things can be difficult in settings where resources are restricted, such as rural areas, low-power industrial installations, and remote sensor networks. This is because of obstacles such as limits on bandwidth and computation capacity, as well as issues around privacy. An investigation into data-transfer protocols that are specifically geared to ensure the privacy of users in edge-cloud collaboration systems is the objective of this study. Application development for the Internet of Things that is scalable and adheres to the principles of data security, dependable connectivity, and resource efficiency is the goal of this project. The hybrid computing architecture is utilized in the research project in order to reduce the quantity of data that is collected at the edge as a result of Internet of Things sensors. This is done prior to the transmission of the raw data to the cloud for further analysis. Differential privacy, homomorphic encryption, secure multi-party computation, and federated learning are all examples of techniques that can maintain the usefulness of the information that is extracted while simultaneously protecting sensitive material. These measures lower the danger of unauthorized access and data loss, especially in limited environments with poor security. The proposed method was tested using simulated IoT networks. Poor bandwidth, unpredictable connectivity, and varied device capabilities plagued these networks. We assessed latency, energy, data reduction, prediction accuracy, and privacy. Edge-based preprocessing, adaptive compression, and encrypted feature extraction cut transmission load by 60% without compromising accuracy. Privacy-enhanced approaches were hard to eavesdrop, guess, and analyze metadata. The collaborative architecture makes the system more scalable and less cloud-dependent, allowing data processing virtually in real time even with poor networks. This study emphasises privacy-preserving and resource-efficient communication in modern IoT systems. Collaborative edge-cloud computing and strengthened data transfer protocols are used to build strong IoT infrastructures in resource-constrained contexts. The findings enable safe, rapid, and easy IoT ecosystem growth for smart agriculture, remote healthcare, and smart transportation systems. © 2026 IEEE.
A488: R0487 | B488: Privacy-Preserving Coalesced Learning: Techniques, Challenges, and Future Directions | C488: Dinesh Kumar, J.; Bansal, N.; Sethi, A. | D488: 2024 | E488: Scopus | F488: Pair 1 | I488: =IF(OR(G488="",H488=""),"",IF(G488=H488,"Yes","No")) | K488: =IF(OR(E488="Snowballing",E488="Other sources"),"n/a",IF(AND(G488="",H488=""),"",IF(OR(G488="",H488=""),"Waiting",IF(G488=H488,G488,IF(AND(G488<>"Exclude",H488<>"Exclude"),"Maybe",IF(J488<>"",J488,"Pending")))))) | P488: Found in: Scopus; IEEE · DOI: 10.1109/ICAC2N63387.2024.10895551 | Q488: Privacy-Preserving Coalesced Learning (PPCL) exist a distributed method to machine learning that allows various plans or administrations to collaboratively order models deficiency allocation raw source, shielding separable privacy. Unlike old-style centralized methodologies, PPCL uses methods like protected collections, other concealment, and homomorphic encryption en route for stopping subtle source leakage. Secure aggregation syndicates separate idea updates securely, discrepancy privacy vaccinates noise to avoid model re-identification, and homomorphic encryption allows encrypted calculations. Despite its assurance, PPCL faces several tests. Communication above from recurrent informs can be heavy, scalability problems arise as contributor number grows, and combative outbreaks may deed system susceptibilities. Additionally, device and data heterogeneity present hurdles to attaining steady truthfulness and impartiality. Future research in PPCL aims to address these tests by improving scalability, enhancing communication, and improving security. These progressions could enlarge PPCL's application to privacy-sensitive areas like healthcare and finance, supporting secure, decentralized data-driven inventions. © 2024 IEEE.
A489: R0488 | B489: Retina-Mesh: A Reconfigurable Silicon-Immunity Architecture for Federated Vision | C489: Xinyi, L.; Zhongtao, C.; Hongze, Q.; Yunzhou, J.; Yanli, Y. | D489: 2026 | E489: Scopus | F489: Pair 2 | I489: =IF(OR(G489="",H489=""),"",IF(G489=H489,"Yes","No")) | K489: =IF(OR(E489="Snowballing",E489="Other sources"),"n/a",IF(AND(G489="",H489=""),"",IF(OR(G489="",H489=""),"Waiting",IF(G489=H489,G489,IF(AND(G489<>"Exclude",H489<>"Exclude"),"Maybe",IF(J489<>"",J489,"Pending")))))) | P489: Found in: Scopus; IEEE · DOI: 10.1109/ACCESS.2026.3705226 | Q489: Federated learning (FL) enables collaborative model training across hospitals without sharing patient data, yet model updates remain vulnerable to privacy attacks that can reconstruct sensitive medical images. This paper introduces Retina-Mesh, a hardware-software co-designed architecture that enforces patient privacy at the silicon level. Our key insight is that by executing all privacy-critical computations - feature extraction, attention modeling, and feature fusion - directly on reconfigurable FPGA hardware, we eliminate the software-side attack surfaces exploited by membership inference and model inversion attacks. The architecture operates in three stages: (1) a local objectness detector identifies diagnostically important regions without exposing raw images; (2) a secure attention mechanism collaboratively models radiologist gaze patterns across institutions under homomorphic encryption; and (3) an on-chip hypergraph module fuses high-order anatomical features entirely within the FPGA's secure boundary. Differential privacy with strict guarantees (ϵ =0.5, δ =10-5 ) is enforced at the aggregation stage. Evaluated on 12,000 CT scans across 10 simulated hospitals, Retina-Mesh reduces membership inference attack accuracy to near-random levels (52.3%) and increases model inversion error by 8.6×, while preserving 93.5% of diagnostically critical regions at 24.1 ms latency and 19.5 W power consumption. These results demonstrate that hardware-enforced privacy can meet the simultaneous demands of security, diagnostic accuracy, and real-time clinical performance. © 2013 IEEE.
A490: R0489 | B490: PRIVACY-PRESERVING CLOUD DATA MINING USING HOMOMORPHIC ENCRYPTION-BASED LOGISTIC REGRESSION | C490: SINGH, A.; ALPHY, A. | D490: 2025 | E490: Scopus | F490: Pair 3 | I490: =IF(OR(G490="",H490=""),"",IF(G490=H490,"Yes","No")) | K490: =IF(OR(E490="Snowballing",E490="Other sources"),"n/a",IF(AND(G490="",H490=""),"",IF(OR(G490="",H490=""),"Waiting",IF(G490=H490,G490,IF(AND(G490<>"Exclude",H490<>"Exclude"),"Maybe",IF(J490<>"",J490,"Pending")))))) | P490: Found in: Scopus | Q490: Because scalable, secure machine learning in untrusted cloud environments is critical today, existing privacypreserving approaches—such as anonymization and differential privacy—often compromise model utility, and prior homomorphic encryption (HE) solutions for logistic regression suffer from high computational overhead, partial encryption, or poor scalability. To address these limitations, we propose a fully homomorphic encryption (FHE)-based logistic regression framework that ensures end-to-end data confidentiality without decryption and supports fully encrypted training and inference. We evaluate our approach on the UCI Heart Disease dataset, achieving 84.2% classification accuracy, with less than 2% degradation compared to plaintext models, while substantially reducing computational overhead relative to recent HE-based techniques. Our analysis explores privacy-accuracy-computation trade-offs and demonstrates a practical and efficient balance between these competing objectives. These results indicate that FHE-enabled logistic regression can deliver high accuracy in privacy-sensitive domains such as healthcare without prohibitive performance costs. This framework paves the way for broader adoption of secure, privacy-preserving machine learning on cloud platforms, offering a dependable solution for organizations seeking to analyse sensitive data securely. © Little Lion Scientific
... A1046: R1045 | B1046: Secure logistic regression based on homomorphic encryption: design and evaluation | C1046: Kim M; Song Y; Wang S; Xia Y; Jiang X | D1046: 2018 | E1046: Other sources | F1046: Pair 3 | I1046: =IF(OR(G1046="",H1046=""),"",IF(G1046=H1046,"Yes","No")) | K1046: =IF(OR(E1046="Snowballing",E1046="Other sources"),"n/a",IF(AND(G1046="",H1046=""),"",IF(OR(G1046="",H1046=""),"Waiting",IF(G1046=H1046,G1046,IF(AND(G1046<>"Exclude",H1046<>"Exclude"),"Maybe",IF(J1046<>"",J1046,"Pending")))))) -> n/a | P1046: Known paper from the protocol search check, not retrieved by any database search (SLR v4 change 4, approved by Abdullah 10 Oct 2026). JMIR Medical Informatics 6(2), e19. PMID: 29666041. Goes straight to full text. | Q1046: (Not in the search exports: see PubMed PMID 29666041.)
